qoqo_pyquest/__init__.py
qoqo_pyquest/__version__.py
qoqo_pyquest/backend/__init__.py
qoqo_pyquest/backend/pyquest_cffi_backend.py
qoqo_pyquest/interface/__init__.py
qoqo_pyquest/interface/pyquest_interface.py
qoqo_pyquest-0.4.1.dist-info/LICENSE
qoqo_pyquest-0.4.1.dist-info/METADATA
qoqo_pyquest-0.4.1.dist-info/WHEEL
qoqo_pyquest-0.4.1.dist-info/top_level.txt
qoqo_pyquest-0.4.1.dist-info/RECORD
