Metadata-Version: 2.1
Name: qoqo-pyquest
Version: 0.4.1
Summary: Quantum Computing Base Package
Home-page: https://quantumsimulations.de
Author: HQS Quantum Simulations
Author-email: info@quantumsimulations.de
License: Apache-2.0
Platform: UNKNOWN
Requires-Python: >=3.7
License-File: LICENSE
Requires-Dist: qoqo (>=0.10.0)
Requires-Dist: pyquest-cffi (>=3.1.0)
Requires-Dist: qoqo-calculator-pyo3 (>=0.6)
Requires-Dist: numpy
